quick_start_py/__init__.py
quick_start_py/env.py
quick_start_py/main.py
quick_start_py/say_hello.py
kgesh_kgesh_sam_hello_1_py-0.0.1.dist-info/METADATA
kgesh_kgesh_sam_hello_1_py-0.0.1.dist-info/WHEEL
kgesh_kgesh_sam_hello_1_py-0.0.1.dist-info/entry_points.txt
kgesh_kgesh_sam_hello_1_py-0.0.1.dist-info/top_level.txt
kgesh_kgesh_sam_hello_1_py-0.0.1.dist-info/RECORD
