Metadata-Version: 2.4
Name: kgesh-kgesh-sam-hello-1-py
Version: 0.0.1
Summary: Say hello to user - Python MCP stdio server
Author-email: Deploxy <hello@deploxy.com>
License: MIT
Keywords: deploxy,mcp,stdio-mcp-server,stdio-mcp-proxy,stdio-mcp-to-serverless
Requires-Python: >=3.8
Requires-Dist: mcp>=1.11.1
Provides-Extra: dev
Requires-Dist: black; extra == "dev"
Requires-Dist: mypy; extra == "dev"
Requires-Dist: pytest; extra == "dev"
